get_commit/__init__.py
get_commit/__main__.py
get_commit/main.py
get_commit-0.1.1.dist-info/METADATA
get_commit-0.1.1.dist-info/WHEEL
get_commit-0.1.1.dist-info/entry_points.txt
get_commit-0.1.1.dist-info/RECORD
